lazy_main/__init__.py
lazy_main/flag.py
lazy_main/lazy_main.py
lazy_main/loop.py
lazy_main-0.6.2.dist-info/METADATA
lazy_main-0.6.2.dist-info/WHEEL
lazy_main-0.6.2.dist-info/RECORD
